{
  "default-registry": {
    "kind": "git",
    "repository": "https://github.com/Microsoft/vcpkg",
    "baseline": "fc6345e114c2e2c4f9714037340ccb08326b3e8c"
  },
  "registries": [
    {
      "kind": "git",
      "repository": "https://github.com/microsoft/vcpkg",
      "baseline": "7ef729383ab801504035a4445b6dbca18c8865c8",
      "packages": [ "boost-modular-build-helper" ]
    },
    {
      "kind": "git",
      "repository": "https://github.com/Microsoft/vcpkg",
      "baseline": "61f610845fb206298a69f708104a51d651872877",
      "packages": [ "boost*", "boost-*" ]
    }
  ]
  }